source/__init__.py
source/main.py
source/lib/Argument.py
source/lib/__init__.py
FileInfo_Video_Audio-0.1.3.dist-info/METADATA
FileInfo_Video_Audio-0.1.3.dist-info/WHEEL
FileInfo_Video_Audio-0.1.3.dist-info/entry_points.txt
FileInfo_Video_Audio-0.1.3.dist-info/top_level.txt
FileInfo_Video_Audio-0.1.3.dist-info/RECORD
