Metadata-Version: 2.1
Name: FileInfo-Video-Audio
Version: 0.1.3
Summary: In this tool is help to get the properties of the Audio and Video files
Home-page: https://git.selfmade.ninja/SRIDHARDSCV/collage_sem_4_python_project_cli_file_details
Author: Sridhar
Author-email: dcsvsridhar@gmail.com
License: UNKNOWN
Platform: UNKNOWN
